pygments_style_rrt/style.py
pygments_style_rrt-1.3.dist-info/licenses/LICENSE
pygments_style_rrt-1.3.dist-info/METADATA
pygments_style_rrt-1.3.dist-info/WHEEL
pygments_style_rrt-1.3.dist-info/entry_points.txt
pygments_style_rrt-1.3.dist-info/top_level.txt
pygments_style_rrt-1.3.dist-info/RECORD
