Metadata-Version: 2.4
Name: pygments-style-rrt
Version: 1.3
Summary: RRT's basic colourful Pygments style
Author-email: Reuben Thomas <rrt@sc3d.org>
License: MIT
Project-URL: Homepage, https://github.com/rrthomas/pygments-style-rrt
Classifier: Environment :: Console
Classifier: Programming Language :: Python :: 3
Requires-Python: >=3.8
License-File: LICENSE
Requires-Dist: pygments
Dynamic: license-file
